{"kind":"identitytoolkit#DownloadAccountResponse","users":[{"localId":"2tPkXS6XzlhdmfAIymZno98WsxTD","lastLoginAt":"1761587232785","emailVerified":true,"email":"test11@gmail.com","salt":"fakeSaltYOZUGaHfLhQOLPILAzEx","passwordHash":"fakeHash:salt=fakeSaltYOZUGaHfLhQOLPILAzEx:password=test2025","passwordUpdatedAt":1761587203407,"validSince":"1761587203","createdAt":"1761587203407","providerUserInfo":[{"providerId":"password","email":"test11@gmail.com","federatedId":"test11@gmail.com","rawId":"test11@gmail.com","displayName":"Test Test"}],"lastRefreshAt":"2025-10-27T18:42:40.767Z","displayName":"Test Test","customAttributes":"{\"role\":\"client\"}"},{"localId":"Q4JHUWup0NrfbpWw9TrXbumdjPKb","lastLoginAt":"1761591478238","emailVerified":true,"email":"test@gmail.com","salt":"fakeSaltwQmH8tfD9qUB8jYr2lSM","passwordHash":"fakeHash:salt=fakeSaltwQmH8tfD9qUB8jYr2lSM:password=test2025","passwordUpdatedAt":1761591459697,"validSince":"1761591459","createdAt":"1761591459696","providerUserInfo":[{"providerId":"password","email":"test@gmail.com","federatedId":"test@gmail.com","rawId":"test@gmail.com","displayName":"TEST TEST"}],"lastRefreshAt":"2025-10-27T18:57:58.239Z","displayName":"TEST TEST","customAttributes":"{\"role\":\"client\"}"},{"localId":"RvGaEj7IBXqqus14ykt83b7bg4LC","lastLoginAt":"1761587356374","displayName":"Vincenzo","photoUrl":"","emailVerified":true,"phoneNumber":"+3939208459987","email":"enzo360@test.it","salt":"fakeSaltFSkj6yeYcSYVvU8O5wsP","passwordHash":"fakeHash:salt=fakeSaltFSkj6yeYcSYVvU8O5wsP:password=test2025","passwordUpdatedAt":1761587348959,"validSince":"1761587348","createdAt":"1761587320997","providerUserInfo":[{"providerId":"password","email":"enzo360@test.it","federatedId":"enzo360@test.it","rawId":"enzo360@test.it","displayName":"Vincenzo","photoUrl":""},{"providerId":"phone","phoneNumber":"+3939208459987","rawId":"+3939208459987"}],"customAttributes":"{\"role\":\"admin\",\"salonIds\":[\"test_1761587381016\"]}","lastRefreshAt":"2025-10-27T18:44:16.841Z","initialEmail":"enzo360@hotmail.it"}]}